pytestqml/__init__.py
pytestqml/exceptions.py
pytestqml/hooks.py
pytestqml/nodes.py
pytestqml/plugin.py
pytestqml/qmlbot.py
pytestqml/qt.py
pytestqml/reporting.py
pytestqml/PyTest/SignalSpy.qml
pytestqml/PyTest/TestCase.qml
pytestqml/PyTest/errors.mjs
pytestqml/PyTest/qmldir
pytestqml/PyTest/qtest.mjs
pytest_qml-0.4.0.dist-info/LICENSE
pytest_qml-0.4.0.dist-info/METADATA
pytest_qml-0.4.0.dist-info/WHEEL
pytest_qml-0.4.0.dist-info/entry_points.txt
pytest_qml-0.4.0.dist-info/top_level.txt
pytest_qml-0.4.0.dist-info/RECORD
