Metadata-Version: 2.1
Name: pytest-qml
Version: 0.4.0
Summary: Run QML Tests with pytest
Home-page: https://github.com/jgirardet/pytest-qml
Author: Jimmy Girardet
Author-email: ijkl@netc.fr
Maintainer: Jimmy Girardet
Maintainer-email: ijkl@netc.fr
License: GNU GPL v3.0
Platform: UNKNOWN
Classifier: Development Status :: 4 - Beta
Classifier: Framework :: Pytest
Classifier: Intended Audience :: Developers
Classifier: Topic :: Software Development :: Testing
Classifier: Programming Language :: Python
Classifier: Programming Language :: Python :: 3
Classifier: Programming Language :: Python :: 3.6
Classifier: Programming Language :: Python :: 3.7
Classifier: Programming Language :: Python :: 3.8
Classifier: Programming Language :: Python :: 3 :: Only
Classifier: Programming Language :: Python :: Implementation :: CPython
Classifier: License :: OSI Approved :: GNU General Public License v3 (GPLv3)
Requires-Python: >=3.6
Requires-Dist: pytest (>=6.0.0)
Requires-Dist: termcolor
